MANIFEST.in
README.md
VERSION
requirements.txt
setup.cfg
setup.py
bin/compose-watcher
compose_watcher.egg-info/PKG-INFO
compose_watcher.egg-info/SOURCES.txt
compose_watcher.egg-info/dependency_links.txt
compose_watcher.egg-info/requires.txt
compose_watcher.egg-info/top_level.txt
docker_compose_watcher/__init__.py
docker_compose_watcher/__main__.py
docker_compose_watcher/cli.py
docker_compose_watcher/constants.py
docker_compose_watcher/logger.py
docker_compose_watcher/main.py
docker_compose_watcher/support.py
docker_compose_watcher/types.py