Metadata-Version: 2.1
Name: compose-watcher
Version: 1.2.5
Summary: compose-watcher
Home-page: https://github.com/remorses/compose-watcher
Author: Tommaso De Rossi
Author-email: daer.tommy@gmail.com
License: Apache Software License 2.0
Keywords: docker-compose,watcher,watch
Platform: UNKNOWN
Classifier: Intended Audience :: Information Technology
Classifier: Programming Language :: Python :: 3
Classifier: Programming Language :: Python :: 3.6
Classifier: Programming Language :: Python :: 3.7
